README.md
setup.py
rasterfairy/__init__.py
rasterfairy/coonswarp.py
rasterfairy/images2gif.py
rasterfairy/prime.py
rasterfairy/rasterfairy.py
rasterfairy/rfoptimizer.py
yale_dhlab_rasterfairy.egg-info/PKG-INFO
yale_dhlab_rasterfairy.egg-info/SOURCES.txt
yale_dhlab_rasterfairy.egg-info/dependency_links.txt
yale_dhlab_rasterfairy.egg-info/requires.txt
yale_dhlab_rasterfairy.egg-info/top_level.txt